bi_etl/.coveragerc
bi_etl/.pylintrc
bi_etl/__init__.py
bi_etl/conversions.py
bi_etl/example_config.ini
bi_etl/example_config_shared.ini
bi_etl/memory_size.py
bi_etl/statement_queue.py
bi_etl/statistics.py
bi_etl/timer.py
bi_etl/version.py
bi_etl/boto3_helper/__init__.py
bi_etl/boto3_helper/dynamodb.py
bi_etl/boto3_helper/lambdas.py
bi_etl/boto3_helper/s3.py
bi_etl/boto3_helper/session.py
bi_etl/boto3_helper/ssm.py
bi_etl/bulk_loaders/__init__.py
bi_etl/bulk_loaders/bulk_loader.py
bi_etl/bulk_loaders/bulk_loader_exception.py
bi_etl/bulk_loaders/postgresql_bulk_load_config.py
bi_etl/bulk_loaders/postgresql_copy.py
bi_etl/bulk_loaders/redshift_s3_avro_loader.py
bi_etl/bulk_loaders/redshift_s3_base.py
bi_etl/bulk_loaders/redshift_s3_csv_loader.py
bi_etl/bulk_loaders/redshift_s3_json_loader.py
bi_etl/bulk_loaders/redshift_s3_parquet_loader.py
bi_etl/bulk_loaders/s3_bulk_load_config.py
bi_etl/bulk_loaders/sql_server_bcp.py
bi_etl/components/__init__.py
bi_etl/components/csv_writer.py
bi_etl/components/csvreader.py
bi_etl/components/data_analyzer.py
bi_etl/components/etlcomponent.py
bi_etl/components/hst_table.py
bi_etl/components/hst_table_source_based.py
bi_etl/components/pyarrow_dataset_reader.py
bi_etl/components/readonlytable.py
bi_etl/components/sqlquery.py
bi_etl/components/table.py
bi_etl/components/w3c_reader.py
bi_etl/components/xlsx_reader.py
bi_etl/components/xlsx_writer.py
bi_etl/components/get_next_key/__init__.py
bi_etl/components/get_next_key/base_table_memory.py
bi_etl/components/get_next_key/local_table_memory.py
bi_etl/components/get_next_key/shared_table_memory.py
bi_etl/components/get_next_key/shared_table_memory_manager.py
bi_etl/components/row/__init__.py
bi_etl/components/row/cached_frozenset.py
bi_etl/components/row/column_difference.py
bi_etl/components/row/row.py
bi_etl/components/row/row_case_insensitive.py
bi_etl/components/row/row_iteration_header.py
bi_etl/components/row/row_iteration_header_case_insensitive.py
bi_etl-1.8.3.dist-info/METADATA
bi_etl-1.8.3.dist-info/WHEEL
bi_etl-1.8.3.dist-info/licenses/license.txt
bi_etl-1.8.3.dist-info/RECORD
